{"颜文字":{"type":"emoticon","container":[{"desc":"'OωO'","icon":"OωO","text":"Author: DIYgod"},{"desc":"'|´・ω・)ノ'","icon":"|´・ω・)ノ","text":"Hi"},{"desc":"'ヾ(≧∇≦*)ゝ'","icon":"ヾ(≧∇≦*)ゝ","text":"开心"},{"desc":"'(☆ω☆)'","icon":"(☆ω☆)","text":"星星眼"},{"desc":"'（╯‵□′）╯︵┴─┴'","icon":"（╯‵□′）╯︵┴─┴","text":"掀桌"},{"desc":"'￣﹃￣'","icon":"￣﹃￣","text":"流口水"},{"desc":"'(/ω＼)'","icon":"(/ω＼)","text":"捂脸"},{"desc":"'∠( ᐛ 」∠)＿'","icon":"∠( ᐛ 」∠)＿","text":"给跪"},{"desc":"'(๑•̀ㅁ•́ฅ)'","icon":"(๑•̀ㅁ•́ฅ)","text":"Hi"},{"desc":"'→_→'","icon":"→_→","text":"斜眼"},{"desc":"'୧(๑•̀⌄•́๑)૭'","icon":"୧(๑•̀⌄•́๑)૭","text":"加油"},{"desc":"'٩(ˊᗜˋ*)و'","icon":"٩(ˊᗜˋ*)و","text":"有木有WiFi"},{"desc":"'(ノ°ο°)ノ'","icon":"(ノ°ο°)ノ","text":"前方高能预警"},{"desc":"'(´இ皿இ｀)'","icon":"(´இ皿இ｀)","text":"我从未见过如此厚颜无耻之人"},{"desc":"'⌇●﹏●⌇'","icon":"⌇●﹏●⌇","text":"吓死宝宝惹"},{"desc":"'(ฅ´ω`ฅ)'","icon":"(ฅ´ω`ฅ)","text":"已阅留爪"},{"desc":"'(╯°A°)╯︵○○○'","icon":"(╯°A°)╯︵○○○","text":"去吧大师球"},{"desc":"'φ(￣∇￣o)'","icon":"φ(￣∇￣o)","text":"太萌惹"},{"desc":"'ヾ(´･ ･｀｡)ノ'","icon":"ヾ(´･ ･｀｡)ノ","text":"咦咦咦"},{"desc":"'( ง ᵒ̌皿ᵒ̌)ง⁼³₌₃'","icon":"( ง ᵒ̌皿ᵒ̌)ง⁼³₌₃","text":"气呼呼"},{"desc":"'(ó﹏ò｡)'","icon":"(ó﹏ò｡)","text":"我受到了惊吓"},{"desc":"'Σ(っ °Д °;)っ'","icon":"Σ(っ °Д °;)っ","text":"什么鬼"},{"desc":"'( ,,´･ω･)ﾉ(´っω･｀｡)'","icon":"( ,,´･ω･)ﾉ\"(´っω･｀｡)","text":"安慰"},{"desc":"'╮(╯▽╰)╭'","icon":"╮(╯▽╰)╭","text":"无奈"},{"desc":"'o(*////▽////*)q'","icon":"o(*////▽////*)q","text":"脸红"},{"desc":"'＞﹏＜'","icon":"＞﹏＜","text":"难受"},{"desc":"'( ๑´•ω•) ﾉ(ㆆᴗㆆ)'","icon":"( ๑´•ω•) ﾉ(ㆆᴗㆆ)","text":"摸摸头"}]}}